{"name":"Btween","tagline":"Javascript Engine for Tweening Along Bézier Curves","body":"btween.js\r\n=========\r\n\r\n#### Bézier TWEENing (BTWEEN) Javascript Engine ####\r\n\r\nA quick and easy library for creating smooth animation paths along Bézier curves. It is recommended that you be [familiar with Bézier curves] (http://en.wikipedia.org/wiki/B%C3%A9zier_curve) before trying to use the library.\r\n\r\n### Usage ###\r\n\r\nDownload the minified library and include it in your html.\r\n\r\n```html\r\n<script src=\"js/btween.min.js\" type=\"text/javascript\"></script>\r\n```\r\n\r\nThe following code creates a Bézier path which a div block will travel along. The path anchors are specified in the addCurve method, and the onUpdate callback function will fire every time the [x,y] values changes.\r\n\r\n```html\r\n<script>\r\n\r\n        // Call init() when document body is loaded\r\n        // jQuery: $(document).ready(init);\r\n        // HTML: <body onload=\"init();\">\r\n\r\n        // Must include RequestAnimationFrame.js\r\n        // http://paulirish.com/2011/requestanimationframe-for-smart-animating/\r\n\r\n\tfunction init() {\r\n\r\n\t\tvar output = document.createElement( 'div' );\r\n\t\toutput.style.cssText = 'position: absolute; left: 200px; top: 200px; font-size: 40px';\r\n\t\tdocument.body.appendChild( output );\r\n\r\n                var startPosition = { x: 200, y: 200 };\r\n                var curvePoints = [\r\n                    { x: 200, y: 200  },\r\n                    { x: 500, y: 600  },\r\n                    { x: 500, y: -200 },\r\n                    { x: 800, y: 200  }\r\n                ];\r\n\t\tvar tween = new BTWEEN.Btween( startPosition )\r\n\t\t\t.addCurve( curvePoints, 5000 )\r\n\t\t\t.onUpdate( function () {\r\n\r\n\t\t\t\toutput.innerHTML = '{x:' + Math.round( this.x ) + ',y:' + Math.round( this.y ) + '}';\r\n\t\t\t\toutput.style.left = this.x + 'px';\r\n                                output.style.top = this.y + 'px';\r\n\r\n\t\t\t} )\r\n\t\t\t.start();\r\n\r\n                animate();\r\n\r\n\t}\r\n\r\n\tfunction animate() {\r\n\r\n\t\trequestAnimationFrame( animate );\r\n\t\tBTWEEN.update();\r\n\r\n\t}\r\n\r\n</script>\r\n```\r\n\r\nA tutorial and set of documentation is in the works. Please be patient!\r\n\r\n### FAQ ###\r\n\r\n**Why is this the only answer?**\r\n\r\nNo one has asked any questions yet!\r\n\r\n### Change log ###\r\n\r\n2013 02 14 - **r0**\r\n\r\n* Initial commit ([patr1k](https://github.com/patr1k))","google":"","note":"Don't delete this file! It's used internally to help with page regeneration."}